enc_dotenv/__init__.py
enc_dotenv/main.py
enc_dotenv/py.typed
enc_dotenv/version.py
enc_dotenv-0.0.3.dist-info/LICENSE
enc_dotenv-0.0.3.dist-info/METADATA
enc_dotenv-0.0.3.dist-info/WHEEL
enc_dotenv-0.0.3.dist-info/top_level.txt
enc_dotenv-0.0.3.dist-info/RECORD
