Metadata-Version: 2.1
Name: enc-dotenv
Version: 0.0.3
Summary: encrypted env
Home-page: https://github.com/bhags1981/python-encrypted-dotenv
Author: Sinyu Jung
Author-email: 
License: UNKNOWN
Keywords: encrypted　environment variables,deployments,settings,env,dotenv,configurations,python
Platform: UNKNOWN
Classifier: Development Status :: 2 - Pre-Alpha
Classifier: Programming Language :: Python
Classifier: Programming Language :: Python :: 3.4
Classifier: Programming Language :: Python :: 3.5
Classifier: Programming Language :: Python :: 3.6
Classifier: Programming Language :: Python :: 3.7
Classifier: Programming Language :: Python :: Implementation :: PyPy
Classifier: Intended Audience :: Developers
Classifier: Intended Audience :: System Administrators
Classifier: License :: OSI Approved :: MIT License
Classifier: Operating System :: OS Independent
Classifier: Topic :: System :: Systems Administration
Classifier: Topic :: Utilities
Classifier: Environment :: Web Environment
Requires-Dist: python-dotenv
Requires-Dist: pyAesCrypt
